kuPyLTSpice/__init__.py
kuPyLTSpice/editor/__init__.py
kuPyLTSpice/editor/asc_editor.py
kuPyLTSpice/editor/spice_editor.py
kuPyLTSpice/Histogram.py
kuPyLTSpice/log/__init__.py
kuPyLTSpice/log/logfile_data.py
kuPyLTSpice/log/ltsteps.py
kuPyLTSpice/log/semi_dev_op_reader.py
kuPyLTSpice/LTSteps.py
kuPyLTSpice/raw/__init__.py
kuPyLTSpice/raw/raw_classes.py
kuPyLTSpice/raw/raw_read.py
kuPyLTSpice/raw/raw_write.py
kuPyLTSpice/rawplot.py
kuPyLTSpice/run_server.py
kuPyLTSpice/sim/__init__.py
kuPyLTSpice/sim/ltspice_simulator.py
kuPyLTSpice/sim/process_callback.py
kuPyLTSpice/sim/sim_batch.py
kuPyLTSpice/sim/sim_runner.py
kuPyLTSpice/sim/sim_stepping.py
kuPyLTSpice/sim/tookit/montecarlo.py
kuPyLTSpice/sim/tookit/worst_case.py
kuPyLTSpice/utils/detect_encoding.py
kuPyLTSpice/utils/sweep_iterators.py
kupyltspice-1.0.0.dist-info/LICENSE
kupyltspice-1.0.0.dist-info/METADATA
kupyltspice-1.0.0.dist-info/WHEEL
kupyltspice-1.0.0.dist-info/RECORD
