Metadata-Version: 2.1
Name: kuPyLTSpice
Version: 1.0.0
Summary: A modified version of PyLTSpice tools to Automate LTSpice simulations
Home-page: https://github.com/RK0429/kuPyLTSpice
License: GPL-3.0-only
Keywords: ltspice,simulation,automation,kupyltspice
Author: Ryota Kobayashi
Author-email: s.woods.m.29@gmail.com
Requires-Python: >=3.10,<4.0
Classifier: License :: OSI Approved :: GNU General Public License v3 (GPLv3)
Classifier: Programming Language :: Python :: 3
Classifier: Programming Language :: Python :: 3.10
Classifier: Programming Language :: Python :: 3.11
Classifier: Programming Language :: Python :: 3.12
Classifier: Programming Language :: Python :: 3.13
Requires-Dist: kupicelib (>=1.0.0,<2.0.0)
Requires-Dist: spicelib (>=1.4.1)
Project-URL: Author, https://www.ryota.com/
Project-URL: Bug Tracker, https://github.com/RK0429/kuPyLTSpice/issues
Project-URL: Original Project, https://github.com/nunobrum/PyLTSpice
Project-URL: Repository, https://github.com/RK0429/kuPyLTSpice
